MANIFEST.in
README.rst
bootstrap-buildout.py
buildout.cfg
setup.py
version.txt
antispoofing/__init__.py
antispoofing.clientspec.egg-info/PKG-INFO
antispoofing.clientspec.egg-info/SOURCES.txt
antispoofing.clientspec.egg-info/dependency_links.txt
antispoofing.clientspec.egg-info/entry_points.txt
antispoofing.clientspec.egg-info/requires.txt
antispoofing.clientspec.egg-info/top_level.txt
antispoofing/clientspec/__init__.py
antispoofing/clientspec/helpers/__init__.py
antispoofing/clientspec/helpers/database.py
antispoofing/clientspec/helpers/gmm_operations.py
antispoofing/clientspec/helpers/score_manipulate.py
antispoofing/clientspec/helpers/utils.py
antispoofing/clientspec/script/__init__.py
antispoofing/clientspec/script/map_adapt_per_client.py
antispoofing/clientspec/script/naive_likelihood.py
antispoofing/clientspec/script/naive_likelihood_clientspecmodel.py
antispoofing/clientspec/script/naive_likelihood_cohortmodels.py
antispoofing/clientspec/script/naive_likelihood_ratio.py
antispoofing/clientspec/script/naive_modelling.py
antispoofing/clientspec/script/score_evaluation_crossdb.py
antispoofing/clientspec/script/scores_box_plot.py
antispoofing/clientspec/script/svm_clientspec_eval.py
antispoofing/clientspec/script/svm_clientspec_train.py