Metadata-Version: 1.0
Name: antispoofing.clientspec
Version: 1.0.3
Summary: Building client-specific models for anti-spoofing
Home-page: http://github.com/bioidiap/antispoofing.clientspec
Author: Ivana Chingovska
Author-email: Ivana Chingovska <ivana.chingovska@idiap.ch>
License: LICENSE.txt
Platform: UNKNOWN
